nanonis_load/__init__.py
nanonis_load/didv.py
nanonis_load/dual_gate.py
nanonis_load/grid.py
nanonis_load/interactive_colorplot.py
nanonis_load/magnetoconductance.py
nanonis_load/sxm.py
nanonis_load/util.py
nanonis_load-3.0.2.dist-info/LICENSE
nanonis_load-3.0.2.dist-info/METADATA
nanonis_load-3.0.2.dist-info/SOURCES-DESKTOP-3NSDU6F.txt
nanonis_load-3.0.2.dist-info/WHEEL
nanonis_load-3.0.2.dist-info/top_level.txt
nanonis_load-3.0.2.dist-info/RECORD
